javascript_data_files/__init__.py
javascript_data_files/decoder.py
javascript_data_files/encoder.py
javascript_data_files/py.typed
javascript_data_files/validate_type.py
javascript_data_files-1.4.1.dist-info/licenses/LICENSE
javascript_data_files-1.4.1.dist-info/METADATA
javascript_data_files-1.4.1.dist-info/WHEEL
javascript_data_files-1.4.1.dist-info/top_level.txt
javascript_data_files-1.4.1.dist-info/RECORD
