Metadata-Version: 2.4
Name: javascript_data_files
Version: 1.4.1
Summary: Work with JSON which is stored as a value in a JavaScript file
Author-email: Alex Chan <alex@alexwlchan.net>
Maintainer-email: Alex Chan <alex@alexwlchan.net>
License-Expression: MIT
Project-URL: Homepage, https://github.com/alexwlchan/python-js-files
Project-URL: Changelog, https://github.com/alexwlchan/python-js-files/blob/main/CHANGELOG.md
Classifier: Development Status :: 5 - Production/Stable
Classifier: Programming Language :: Python :: 3.12
Requires-Python: >=3.12
License-File: LICENSE
Provides-Extra: typed
Requires-Dist: pydantic; extra == "typed"
Dynamic: license-file
